pyvguicom/__init__.py
pyvguicom/browsewin.py
pyvguicom/comline.py
pyvguicom/custwidg.py
pyvguicom/pgbox.py
pyvguicom/pgbutt.py
pyvguicom/pgentry.py
pyvguicom/pggui.py
pyvguicom/pgsel.py
pyvguicom/pgsimp.py
pyvguicom/pgtests.py
pyvguicom/pgtextview.py
pyvguicom/pgutils.py
pyvguicom/pgwkit.py
pyvguicom/plug.py
pyvguicom/docs/__index__.py
pyvguicom/docs/browsewin.html
pyvguicom/docs/htmledit.html
pyvguicom/docs/pgbox.html
pyvguicom/docs/pgbutt.html
pyvguicom/docs/pgentry.html
pyvguicom/docs/pggui.html
pyvguicom/docs/pgsel.html
pyvguicom/docs/pgsimp.html
pyvguicom/docs/pgtextview.html
pyvguicom/docs/pgutils.html
pyvguicom/docs/pgwkit.html
pyvguicom/docs/sutil.html
pyvguicom-1.3.9.dist-info/METADATA
pyvguicom-1.3.9.dist-info/WHEEL
pyvguicom-1.3.9.dist-info/top_level.txt
pyvguicom-1.3.9.dist-info/RECORD
