Metadata-Version: 2.4
Name: pyvguicom
Version: 1.3.9
Summary: High power secure server GUI utility helpers.
Home-page: https://github.com/pglen/pyguicom.git
Author: Peter Glen
Author-email: peterglen99@gmail.com
Classifier: Development Status :: 6 - Mature
Classifier: Intended Audience :: End Users/Desktop
Classifier: Intended Audience :: Developers
Classifier: Intended Audience :: System Administrators
Classifier: License :: OSI Approved :: Python Software Foundation License
Classifier: Operating System :: Microsoft :: Windows
Classifier: Operating System :: POSIX
Classifier: Programming Language :: Python
Classifier: Topic :: Software Development :: Libraries
Requires-Python: >=3
Dynamic: author
Dynamic: author-email
Dynamic: classifier
Dynamic: description
Dynamic: description-content-type
Dynamic: home-page
Dynamic: requires-python
Dynamic: summary
